[
  {
    "id": "1782038794288",
    "symbol": "TNSRUSDT",
    "label": "انعكاس 4h DCA",
    "strategy": "dca",
    "timeframe": "4h",
    "side": "buy",
    "entry": 0.0494,
    "stop": 0.025908723908017867,
    "stop_orig": 0.025908723908017867,
    "targets": [
      0.0612624,
      0.0705006,
      0.0807
    ],
    "risk": 0.023491276091982132,
    "opened_at": "2026-06-21T22:03:14",
    "status": "open",
    "hits": [],
    "breakeven": false,
    "remaining": 1.0,
    "realized_R": 0.0,
    "result_R": null,
    "events": [],
    "last_ts": "2026-06-22 15:59:59.999000",
    "closed_at": null
  },
  {
    "id": "1782054194497",
    "symbol": "BICOUSDT",
    "label": "RSI80 · 1d",
    "strategy": "classic",
    "timeframe": "1d",
    "side": "buy",
    "entry": 0.0627,
    "stop": 0.05498868972339402,
    "stop_orig": 0.05498868972339402,
    "targets": [
      0.0750488,
      0.0907572,
      0.1361572
    ],
    "risk": 0.007711310276605987,
    "opened_at": "2026-06-21T22:03:14",
    "status": "closed",
    "hits": [],
    "breakeven": false,
    "remaining": 0.0,
    "realized_R": -1.0,
    "result_R": -1.0,
    "events": [
      {
        "ts": "2026-06-21 23:59:59.999000",
        "type": "sl",
        "price": 0.05498868972339402,
        "R": -1.0
      }
    ],
    "last_ts": "2026-06-21 23:59:59.999000",
    "closed_at": "2026-06-22T12:11:31"
  },
  {
    "id": "1782061015487",
    "symbol": "2ZUSDT",
    "label": "RSI70 · 15m",
    "strategy": "classic",
    "timeframe": "15m",
    "side": "buy",
    "entry": 0.07986,
    "stop": 0.07986,
    "stop_orig": 0.07805148790556007,
    "targets": [
      0.08139408,
      0.08334552,
      0.08898552
    ],
    "risk": 0.0018085120944399263,
    "opened_at": "2026-06-21T22:03:14",
    "status": "closed",
    "hits": [
      1
    ],
    "breakeven": true,
    "remaining": 0.0,
    "realized_R": 5.684230717397323,
    "result_R": 5.684,
    "events": [
      {
        "ts": "2026-06-21 16:59:59.999000",
        "type": "tp1_be",
        "price": 0.08139408,
        "R": 0.848
      },
      {
        "ts": "2026-06-21 16:59:59.999000",
        "type": "bear_div",
        "price": 0.09014,
        "R": 5.684
      }
    ],
    "last_ts": "2026-06-21 16:59:59.999000",
    "closed_at": "2026-06-21T22:03:18"
  },
  {
    "id": "1782061035777",
    "symbol": "2ZUSDT",
    "label": "RSI70 · 1h",
    "strategy": "classic",
    "timeframe": "1h",
    "side": "buy",
    "entry": 0.07856,
    "stop": 0.07856,
    "stop_orig": 0.07639814418865869,
    "targets": [
      0.08159008,
      0.08544452,
      0.09658452
    ],
    "risk": 0.0021618558113413178,
    "opened_at": "2026-06-21T22:03:14",
    "status": "closed",
    "hits": [
      1
    ],
    "breakeven": true,
    "remaining": 0.0,
    "realized_R": 0.0,
    "result_R": 0.0,
    "events": [
      {
        "ts": "2026-06-21 16:59:59.999000",
        "type": "tp1_be",
        "price": 0.08159008,
        "R": 1.402
      },
      {
        "ts": "2026-06-21 19:59:59.999000",
        "type": "be_sl",
        "price": 0.07856,
        "R": 0.0
      }
    ],
    "last_ts": "2026-06-21 19:59:59.999000",
    "closed_at": "2026-06-21T22:03:20"
  },
  {
    "id": "1782061036137",
    "symbol": "LTCUSDT",
    "label": "RSI70 · 1h",
    "strategy": "classic",
    "timeframe": "1h",
    "side": "buy",
    "entry": 45.93,
    "stop": 45.495823393275344,
    "stop_orig": 45.495823393275344,
    "targets": [
      46.44408,
      47.09802,
      48.98802
    ],
    "risk": 0.4341766067246553,
    "opened_at": "2026-06-21T22:03:14",
    "status": "closed",
    "hits": [],
    "breakeven": false,
    "remaining": 0.0,
    "realized_R": -1.0,
    "result_R": -1.0,
    "events": [
      {
        "ts": "2026-06-21 16:59:59.999000",
        "type": "sl",
        "price": 45.495823393275344,
        "R": -1.0
      }
    ],
    "last_ts": "2026-06-21 16:59:59.999000",
    "closed_at": "2026-06-21T22:03:21"
  },
  {
    "id": "1782061053927",
    "symbol": "SAGAUSDT",
    "label": "RSI70 · 4h",
    "strategy": "classic",
    "timeframe": "4h",
    "side": "buy",
    "entry": 0.01596,
    "stop": 0.01596,
    "stop_orig": 0.014978806770639987,
    "targets": [
      0.0168848,
      0.0180612,
      0.0214612
    ],
    "risk": 0.0009811932293600119,
    "opened_at": "2026-06-21T22:03:14",
    "status": "closed",
    "hits": [
      1
    ],
    "breakeven": true,
    "remaining": 0.0,
    "realized_R": 0.0,
    "result_R": 0.0,
    "events": [
      {
        "ts": "2026-06-21 19:59:59.999000",
        "type": "tp1_be",
        "price": 0.0168848,
        "R": 0.943
      },
      {
        "ts": "2026-06-21 23:59:59.999000",
        "type": "be_sl",
        "price": 0.01596,
        "R": 0.0
      }
    ],
    "last_ts": "2026-06-21 23:59:59.999000",
    "closed_at": "2026-06-22T12:11:32"
  },
  {
    "id": "1782079363641",
    "symbol": "TNSRUSDT",
    "label": "RSI70 · 4h",
    "strategy": "classic",
    "timeframe": "4h",
    "side": "buy",
    "entry": 0.0482,
    "stop": 0.04193150483868239,
    "stop_orig": 0.04193150483868239,
    "targets": [
      0.0537216,
      0.0607454,
      0.0810454
    ],
    "risk": 0.006268495161317611,
    "opened_at": "2026-06-21T22:03:14",
    "status": "closed",
    "hits": [],
    "breakeven": false,
    "remaining": 0.0,
    "realized_R": -1.0,
    "result_R": -1.0,
    "events": [
      {
        "ts": "2026-06-22 11:59:59.999000",
        "type": "sl",
        "price": 0.04193150483868239,
        "R": -1.0
      }
    ],
    "last_ts": "2026-06-22 11:59:59.999000",
    "closed_at": "2026-06-22T12:11:33"
  },
  {
    "id": "1782130211849",
    "symbol": "DCRUSDT",
    "label": "RSI70 · 15m",
    "strategy": "classic",
    "timeframe": "15m",
    "side": "buy",
    "entry": 11.93,
    "stop": 11.833549552719532,
    "stop_orig": 11.833549552719532,
    "targets": [
      12.02792,
      12.15248,
      12.51248
    ],
    "risk": 0.0964504472804677,
    "opened_at": "2026-06-22T12:11:28",
    "status": "closed",
    "hits": [],
    "breakeven": false,
    "remaining": 0.0,
    "realized_R": 0.0,
    "result_R": null,
    "events": [
      {
        "ts": "2026-06-22 14:44:59.999000",
        "type": "sl",
        "price": 11.833549552719532,
        "pct": -0.808
      }
    ],
    "last_ts": "2026-06-22 14:44:59.999000",
    "closed_at": "2026-06-22T14:47:08",
    "realized_pct": -0.8084698011774326,
    "exit_price": 11.833549552719532,
    "result_pct": -0.808
  },
  {
    "id": "1782130212663",
    "symbol": "TIAUSDT",
    "label": "RSI70 · 15m",
    "strategy": "classic",
    "timeframe": "15m",
    "side": "buy",
    "entry": 0.3963,
    "stop": 0.3963,
    "stop_orig": 0.3911392248011571,
    "targets": [
      0.4019576,
      0.4091544,
      0.4299544
    ],
    "risk": 0.005160775198842893,
    "opened_at": "2026-06-22T12:11:28",
    "status": "closed",
    "hits": [
      1
    ],
    "breakeven": true,
    "remaining": 0.0,
    "realized_R": 0.0,
    "result_R": 0.0,
    "events": [
      {
        "ts": "2026-06-22 12:29:59.999000",
        "type": "tp1_be",
        "price": 0.4019576,
        "R": 1.096
      },
      {
        "ts": "2026-06-22 12:44:59.999000",
        "type": "be_sl",
        "price": 0.3963,
        "R": 0.0
      }
    ],
    "last_ts": "2026-06-22 12:44:59.999000",
    "closed_at": "2026-06-22T13:23:45"
  },
  {
    "id": "1782130237603",
    "symbol": "WUSDT",
    "label": "RSI70 · 1h",
    "strategy": "classic",
    "timeframe": "1h",
    "side": "buy",
    "entry": 0.01259,
    "stop": 0.01188325767984124,
    "stop_orig": 0.01188325767984124,
    "targets": [
      0.01305784,
      0.01365296,
      0.01537296
    ],
    "risk": 0.0007067423201587604,
    "opened_at": "2026-06-22T12:11:28",
    "status": "closed",
    "hits": [],
    "breakeven": false,
    "remaining": 0.0,
    "realized_R": 0.0,
    "result_R": null,
    "events": [
      {
        "ts": "2026-06-22 13:59:59.999000",
        "type": "sl",
        "price": 0.01188325767984124,
        "pct": -5.614
      }
    ],
    "last_ts": "2026-06-22 13:59:59.999000",
    "closed_at": "2026-06-22T14:02:30",
    "realized_pct": -5.6135212085683905,
    "exit_price": 0.01188325767984124,
    "result_pct": -5.614
  },
  {
    "id": "1782130259464",
    "symbol": "LAYERUSDT",
    "label": "RSI70 · 4h",
    "strategy": "classic",
    "timeframe": "4h",
    "side": "buy",
    "entry": 0.0874,
    "stop": 0.08186154264035365,
    "stop_orig": 0.08186154264035365,
    "targets": [
      0.0937648,
      0.1018612,
      0.1252612
    ],
    "risk": 0.005538457359646351,
    "opened_at": "2026-06-22T12:11:28",
    "status": "closed",
    "hits": [],
    "breakeven": false,
    "remaining": 0.0,
    "realized_R": 0.0,
    "result_R": null,
    "events": [
      {
        "ts": "2026-06-22 15:59:59.999000",
        "type": "sl",
        "price": 0.08186154264035365,
        "pct": -6.337
      }
    ],
    "last_ts": "2026-06-22 15:59:59.999000",
    "closed_at": "2026-06-22T16:02:25",
    "realized_pct": -6.336907734149142,
    "exit_price": 0.08186154264035365,
    "result_pct": -6.337
  },
  {
    "id": "1782130260482",
    "symbol": "WUSDT",
    "label": "RSI70 · 4h",
    "strategy": "classic",
    "timeframe": "4h",
    "side": "buy",
    "entry": 0.01259,
    "stop": 0.011697041168959614,
    "stop_orig": 0.011697041168959614,
    "targets": [
      0.01346856,
      0.01458614,
      0.01781614
    ],
    "risk": 0.0008929588310403868,
    "opened_at": "2026-06-22T12:11:28",
    "status": "closed",
    "hits": [],
    "breakeven": false,
    "remaining": 0.0,
    "realized_R": 0.0,
    "result_R": null,
    "events": [
      {
        "ts": "2026-06-22 15:59:59.999000",
        "type": "sl",
        "price": 0.011697041168959614,
        "pct": -7.093
      }
    ],
    "last_ts": "2026-06-22 15:59:59.999000",
    "closed_at": "2026-06-22T16:02:27",
    "realized_pct": -7.092603900241357,
    "exit_price": 0.011697041168959614,
    "result_pct": -7.093
  },
  {
    "id": "1782134541189",
    "symbol": "GTCUSDT",
    "label": "RSI70 · 15m",
    "strategy": "classic",
    "timeframe": "15m",
    "side": "buy",
    "entry": 0.079,
    "stop": 0.07801254291758881,
    "stop_orig": 0.07801254291758881,
    "targets": [
      0.079816,
      0.080854,
      0.083854
    ],
    "risk": 0.0009874570824111861,
    "opened_at": "2026-06-22T13:23:41",
    "status": "closed",
    "hits": [],
    "breakeven": false,
    "remaining": 0.0,
    "realized_R": -1.0,
    "result_R": -1.0,
    "events": [
      {
        "ts": "2026-06-22 13:29:59.999000",
        "type": "sl",
        "price": 0.07801254291758881,
        "R": -1.0
      }
    ],
    "last_ts": "2026-06-22 13:29:59.999000",
    "closed_at": "2026-06-22T13:32:01"
  },
  {
    "id": "1782134542094",
    "symbol": "LPTUSDT",
    "label": "RSI70 · 15m",
    "strategy": "classic",
    "timeframe": "15m",
    "side": "buy",
    "entry": 1.775,
    "stop": 1.7661522298147174,
    "stop_orig": 1.7661522298147174,
    "targets": [
      1.786696,
      1.801574,
      1.844574
    ],
    "risk": 0.008847770185282489,
    "opened_at": "2026-06-22T13:23:41",
    "status": "closed",
    "hits": [],
    "breakeven": false,
    "remaining": 0.0,
    "realized_R": -1.0,
    "result_R": -1.0,
    "events": [
      {
        "ts": "2026-06-22 13:29:59.999000",
        "type": "sl",
        "price": 1.7661522298147174,
        "R": -1.0
      }
    ],
    "last_ts": "2026-06-22 13:29:59.999000",
    "closed_at": "2026-06-22T13:32:02"
  },
  {
    "id": "1782134569821",
    "symbol": "BREVUSDT",
    "label": "RSI70 · 1h",
    "strategy": "classic",
    "timeframe": "1h",
    "side": "buy",
    "entry": 0.0863,
    "stop": 0.0863,
    "stop_orig": 0.08446060296509166,
    "targets": [
      0.0884488,
      0.0911822,
      0.0990822
    ],
    "risk": 0.0018393970349083466,
    "opened_at": "2026-06-22T13:23:41",
    "status": "open",
    "hits": [
      1
    ],
    "breakeven": true,
    "remaining": 1.0,
    "realized_R": 0.0,
    "result_R": null,
    "events": [
      {
        "ts": "2026-06-22 15:59:59.999000",
        "type": "tp1_be",
        "price": 0.0884488,
        "pct": 2.49
      }
    ],
    "last_ts": "2026-06-22 15:59:59.999000",
    "closed_at": null
  },
  {
    "id": "1782135056791",
    "symbol": "DCRUSDT",
    "label": "RSI70 · 15m",
    "strategy": "classic",
    "timeframe": "15m",
    "side": "buy",
    "entry": 11.97,
    "stop": 11.871793672015462,
    "stop_orig": 11.871793672015462,
    "targets": [
      12.0788,
      12.2172,
      12.6172
    ],
    "risk": 0.09820632798453843,
    "opened_at": "2026-06-22T13:31:56",
    "status": "closed",
    "hits": [],
    "breakeven": false,
    "remaining": 0.0,
    "realized_R": 0.0,
    "result_R": null,
    "events": [
      {
        "ts": "2026-06-22 14:44:59.999000",
        "type": "sl",
        "price": 11.871793672015462,
        "pct": -0.82
      }
    ],
    "last_ts": "2026-06-22 14:44:59.999000",
    "closed_at": "2026-06-22T14:47:11",
    "realized_pct": -0.8204371594364112,
    "exit_price": 11.871793672015462,
    "result_pct": -0.82
  },
  {
    "id": "1782135057251",
    "symbol": "ROSEUSDT",
    "label": "RSI70 · 15m",
    "strategy": "classic",
    "timeframe": "15m",
    "side": "buy",
    "entry": 0.00687,
    "stop": 0.006802726921688806,
    "stop_orig": 0.006802726921688806,
    "targets": [
      0.00694072,
      0.00703068,
      0.00729068
    ],
    "risk": 6.727307831119397e-05,
    "opened_at": "2026-06-22T13:31:56",
    "status": "closed",
    "hits": [],
    "breakeven": false,
    "remaining": 0.0,
    "realized_R": 0.0,
    "result_R": null,
    "events": [
      {
        "ts": "2026-06-22 14:29:59.999000",
        "type": "sl",
        "price": 0.006802726921688806,
        "pct": -0.979
      }
    ],
    "last_ts": "2026-06-22 14:29:59.999000",
    "closed_at": "2026-06-22T14:32:21",
    "realized_pct": -0.9792296697408147,
    "exit_price": 0.006802726921688806,
    "result_pct": -0.979
  },
  {
    "id": "1782135963219",
    "symbol": "ETHUSDT",
    "label": "RSI70 · 15m",
    "strategy": "classic",
    "timeframe": "15m",
    "side": "buy",
    "entry": 1774.08,
    "stop": 1763.8034518177715,
    "stop_orig": 1763.8034518177715,
    "targets": [
      1782.32976,
      1792.82394,
      1823.15394
    ],
    "risk": 10.276548182228453,
    "opened_at": "2026-06-22T13:47:35",
    "status": "closed",
    "hits": [],
    "breakeven": false,
    "remaining": 0.0,
    "realized_R": 0.0,
    "result_R": null,
    "events": [
      {
        "ts": "2026-06-22 14:29:59.999000",
        "type": "sl",
        "price": 1763.8034518177715,
        "pct": -0.579
      }
    ],
    "last_ts": "2026-06-22 14:29:59.999000",
    "closed_at": "2026-06-22T14:32:22",
    "realized_pct": -0.5792606975011528,
    "exit_price": 1763.8034518177715,
    "result_pct": -0.579
  },
  {
    "id": "1782135964547",
    "symbol": "BTCUSDT",
    "label": "RSI70 · 15m",
    "strategy": "classic",
    "timeframe": "15m",
    "side": "buy",
    "entry": 65410.0,
    "stop": 65067.51378716857,
    "stop_orig": 65067.51378716857,
    "targets": [
      65781.552,
      66254.188,
      67620.188
    ],
    "risk": 342.4862128314271,
    "opened_at": "2026-06-22T13:47:35",
    "status": "closed",
    "hits": [],
    "breakeven": false,
    "remaining": 0.0,
    "realized_R": 0.0,
    "result_R": null,
    "events": [
      {
        "ts": "2026-06-22 14:29:59.999000",
        "type": "sl",
        "price": 65067.51378716857,
        "pct": -0.524
      }
    ],
    "last_ts": "2026-06-22 14:29:59.999000",
    "closed_at": "2026-06-22T14:32:23",
    "realized_pct": -0.5235991634787145,
    "exit_price": 65067.51378716857,
    "result_pct": -0.524
  },
  {
    "id": "1782135965823",
    "symbol": "ONGUSDT",
    "label": "RSI70 · 15m",
    "strategy": "classic",
    "timeframe": "15m",
    "side": "buy",
    "entry": 0.04792,
    "stop": 0.04762613923413607,
    "stop_orig": 0.04762613923413607,
    "targets": [
      0.04840688,
      0.04902622,
      0.05081622
    ],
    "risk": 0.0002938607658639278,
    "opened_at": "2026-06-22T13:47:35",
    "status": "closed",
    "hits": [],
    "breakeven": false,
    "remaining": 0.0,
    "realized_R": 0.0,
    "result_R": null,
    "events": [
      {
        "ts": "2026-06-22 14:44:59.999000",
        "type": "sl",
        "price": 0.04762613923413607,
        "pct": -0.613
      }
    ],
    "last_ts": "2026-06-22 14:44:59.999000",
    "closed_at": "2026-06-22T14:47:12",
    "realized_pct": -0.6132319821868276,
    "exit_price": 0.04762613923413607,
    "result_pct": -0.613
  },
  {
    "id": "1782135966245",
    "symbol": "REQUSDT",
    "label": "RSI70 · 15m",
    "strategy": "classic",
    "timeframe": "15m",
    "side": "buy",
    "entry": 0.0581,
    "stop": 0.0581,
    "stop_orig": 0.057384503403640166,
    "targets": [
      0.0587528,
      0.0595832,
      0.0619832
    ],
    "risk": 0.0007154965963598325,
    "opened_at": "2026-06-22T13:47:35",
    "status": "closed",
    "hits": [
      1
    ],
    "breakeven": true,
    "remaining": 0.0,
    "realized_R": 0.0,
    "result_R": null,
    "events": [
      {
        "ts": "2026-06-22 15:29:59.999000",
        "type": "tp1_be",
        "price": 0.0587528,
        "pct": 1.124
      },
      {
        "ts": "2026-06-22 15:44:59.999000",
        "type": "be_sl",
        "price": 0.0581,
        "pct": 0.0
      }
    ],
    "last_ts": "2026-06-22 15:44:59.999000",
    "closed_at": "2026-06-22T15:47:09",
    "realized_pct": 0.0,
    "exit_price": 0.0581,
    "result_pct": 0.0
  },
  {
    "id": "1782135967252",
    "symbol": "STXUSDT",
    "label": "RSI70 · 15m",
    "strategy": "classic",
    "timeframe": "15m",
    "side": "buy",
    "entry": 0.1865,
    "stop": 0.1865,
    "stop_orig": 0.18488594943626274,
    "targets": [
      0.1887304,
      0.1915676,
      0.1997676
    ],
    "risk": 0.001614050563737257,
    "opened_at": "2026-06-22T13:47:35",
    "status": "closed",
    "hits": [
      1
    ],
    "breakeven": true,
    "remaining": 0.0,
    "realized_R": 0.0,
    "result_R": null,
    "events": [
      {
        "ts": "2026-06-22 14:14:59.999000",
        "type": "tp1_be",
        "price": 0.1887304,
        "pct": 1.196
      },
      {
        "ts": "2026-06-22 14:29:59.999000",
        "type": "be_sl",
        "price": 0.1865,
        "pct": 0.0
      }
    ],
    "last_ts": "2026-06-22 14:29:59.999000",
    "closed_at": "2026-06-22T14:32:25",
    "realized_pct": 0.0,
    "exit_price": 0.1865,
    "result_pct": 0.0
  },
  {
    "id": "1782135968753",
    "symbol": "ZECUSDT",
    "label": "RSI70 · 15m",
    "strategy": "classic",
    "timeframe": "15m",
    "side": "buy",
    "entry": 464.24,
    "stop": 458.88728618287564,
    "stop_orig": 458.88728618287564,
    "targets": [
      468.0752,
      472.9538,
      487.0538
    ],
    "risk": 5.352713817124368,
    "opened_at": "2026-06-22T13:47:35",
    "status": "closed",
    "hits": [],
    "breakeven": false,
    "remaining": 0.0,
    "realized_R": 0.0,
    "result_R": null,
    "events": [
      {
        "ts": "2026-06-22 14:29:59.999000",
        "type": "sl",
        "price": 458.88728618287564,
        "pct": -1.153
      }
    ],
    "last_ts": "2026-06-22 14:29:59.999000",
    "closed_at": "2026-06-22T14:32:27",
    "realized_pct": -1.1530057334836223,
    "exit_price": 458.88728618287564,
    "result_pct": -1.153
  },
  {
    "id": "1782135968811",
    "symbol": "VTHOUSDT",
    "label": "RSI70 · 15m",
    "strategy": "classic",
    "timeframe": "15m",
    "side": "buy",
    "entry": 0.000399,
    "stop": 0.000399,
    "stop_orig": 0.0003966443433271019,
    "targets": [
      0.00040145,
      0.00040456,
      0.00041356
    ],
    "risk": 2.355656672898079e-06,
    "opened_at": "2026-06-22T13:47:35",
    "status": "closed",
    "hits": [
      1
    ],
    "breakeven": true,
    "remaining": 0.0,
    "realized_R": 0.0,
    "result_R": null,
    "events": [
      {
        "ts": "2026-06-22 15:14:59.999000",
        "type": "tp1_be",
        "price": 0.00040145,
        "pct": 0.614
      },
      {
        "ts": "2026-06-22 15:44:59.999000",
        "type": "bear_div",
        "price": 0.0004,
        "pct": 0.251
      }
    ],
    "last_ts": "2026-06-22 15:44:59.999000",
    "closed_at": "2026-06-22T15:47:10",
    "realized_pct": 0.2506265664160462,
    "exit_price": 0.0004,
    "result_pct": 0.251
  },
  {
    "id": "1782136866311",
    "symbol": "API3USDT",
    "label": "RSI70 · 15m",
    "strategy": "classic",
    "timeframe": "15m",
    "side": "buy",
    "entry": 0.2655,
    "stop": 0.26363258477533486,
    "stop_orig": 0.26363258477533486,
    "targets": [
      0.2679208,
      0.2710002,
      0.2799002
    ],
    "risk": 0.0018674152246651587,
    "opened_at": "2026-06-22T14:02:27",
    "status": "closed",
    "hits": [],
    "breakeven": false,
    "remaining": 0.0,
    "realized_pct": -0.7033579000622067,
    "result_pct": -0.703,
    "exit_price": 0.26363258477533486,
    "events": [
      {
        "ts": "2026-06-22 14:44:59.999000",
        "type": "sl",
        "price": 0.26363258477533486,
        "pct": -0.703
      }
    ],
    "last_ts": "2026-06-22 14:44:59.999000",
    "closed_at": "2026-06-22T14:47:14"
  },
  {
    "id": "1782136867599",
    "symbol": "AVAXUSDT",
    "label": "RSI70 · 15m",
    "strategy": "classic",
    "timeframe": "15m",
    "side": "buy",
    "entry": 6.463,
    "stop": 6.404277940142037,
    "stop_orig": 6.404277940142037,
    "targets": [
      6.523928,
      6.601432,
      6.825432
    ],
    "risk": 0.058722059857963416,
    "opened_at": "2026-06-22T14:02:27",
    "status": "closed",
    "hits": [],
    "breakeven": false,
    "remaining": 0.0,
    "realized_pct": -0.9085882695027605,
    "result_pct": -0.909,
    "exit_price": 6.404277940142037,
    "events": [
      {
        "ts": "2026-06-22 14:14:59.999000",
        "type": "sl",
        "price": 6.404277940142037,
        "pct": -0.909
      }
    ],
    "last_ts": "2026-06-22 14:14:59.999000",
    "closed_at": "2026-06-22T14:17:30"
  },
  {
    "id": "1782136868095",
    "symbol": "DOGEUSDT",
    "label": "RSI70 · 15m",
    "strategy": "classic",
    "timeframe": "15m",
    "side": "buy",
    "entry": 0.08503,
    "stop": 0.08460945052357442,
    "stop_orig": 0.08460945052357442,
    "targets": [
      0.08544616,
      0.08597554,
      0.08750554
    ],
    "risk": 0.00042054947642557183,
    "opened_at": "2026-06-22T14:02:27",
    "status": "closed",
    "hits": [],
    "breakeven": false,
    "remaining": 0.0,
    "realized_pct": -0.49458952890223673,
    "result_pct": -0.495,
    "exit_price": 0.08460945052357442,
    "events": [
      {
        "ts": "2026-06-22 14:14:59.999000",
        "type": "sl",
        "price": 0.08460945052357442,
        "pct": -0.495
      }
    ],
    "last_ts": "2026-06-22 14:14:59.999000",
    "closed_at": "2026-06-22T14:17:31"
  },
  {
    "id": "1782136869033",
    "symbol": "ICXUSDT",
    "label": "RSI70 · 15m",
    "strategy": "classic",
    "timeframe": "15m",
    "side": "buy",
    "entry": 0.0283,
    "stop": 0.028167131971778236,
    "stop_orig": 0.028167131971778236,
    "targets": [
      0.0285176,
      0.0287944,
      0.0295944
    ],
    "risk": 0.000132868028221763,
    "opened_at": "2026-06-22T14:02:27",
    "status": "closed",
    "hits": [],
    "breakeven": false,
    "remaining": 0.0,
    "realized_pct": -0.4694983329390919,
    "result_pct": -0.469,
    "exit_price": 0.028167131971778236,
    "events": [
      {
        "ts": "2026-06-22 14:29:59.999000",
        "type": "sl",
        "price": 0.028167131971778236,
        "pct": -0.469
      }
    ],
    "last_ts": "2026-06-22 14:29:59.999000",
    "closed_at": "2026-06-22T14:32:28"
  },
  {
    "id": "1782136870471",
    "symbol": "IMXUSDT",
    "label": "RSI70 · 15m",
    "strategy": "classic",
    "timeframe": "15m",
    "side": "buy",
    "entry": 0.1435,
    "stop": 0.1426202972767112,
    "stop_orig": 0.1426202972767112,
    "targets": [
      0.144588,
      0.145972,
      0.149972
    ],
    "risk": 0.0008797027232888,
    "opened_at": "2026-06-22T14:02:27",
    "status": "closed",
    "hits": [],
    "breakeven": false,
    "remaining": 0.0,
    "realized_pct": -0.6130332566472474,
    "result_pct": -0.613,
    "exit_price": 0.1426202972767112,
    "events": [
      {
        "ts": "2026-06-22 14:29:59.999000",
        "type": "sl",
        "price": 0.1426202972767112,
        "pct": -0.613
      }
    ],
    "last_ts": "2026-06-22 14:29:59.999000",
    "closed_at": "2026-06-22T14:32:30"
  },
  {
    "id": "1782136872456",
    "symbol": "QNTUSDT",
    "label": "RSI70 · 15m",
    "strategy": "classic",
    "timeframe": "15m",
    "side": "buy",
    "entry": 73.4,
    "stop": 72.58732365680919,
    "stop_orig": 72.58732365680919,
    "targets": [
      74.3248,
      75.5012,
      78.9012
    ],
    "risk": 0.8126763431908159,
    "opened_at": "2026-06-22T14:02:27",
    "status": "closed",
    "hits": [],
    "breakeven": false,
    "remaining": 0.0,
    "realized_pct": -1.107188478461602,
    "result_pct": -1.107,
    "exit_price": 72.58732365680919,
    "events": [
      {
        "ts": "2026-06-22 14:29:59.999000",
        "type": "sl",
        "price": 72.58732365680919,
        "pct": -1.107
      }
    ],
    "last_ts": "2026-06-22 14:29:59.999000",
    "closed_at": "2026-06-22T14:32:31"
  },
  {
    "id": "1782136873170",
    "symbol": "ROSEUSDT",
    "label": "RSI70 · 15m",
    "strategy": "classic",
    "timeframe": "15m",
    "side": "buy",
    "entry": 0.00687,
    "stop": 0.006800744131456165,
    "stop_orig": 0.006800744131456165,
    "targets": [
      0.00694072,
      0.00703068,
      0.00729068
    ],
    "risk": 6.925586854383565e-05,
    "opened_at": "2026-06-22T14:02:27",
    "status": "closed",
    "hits": [],
    "breakeven": false,
    "remaining": 0.0,
    "realized_pct": -1.008091245179558,
    "result_pct": -1.008,
    "exit_price": 0.006800744131456165,
    "events": [
      {
        "ts": "2026-06-22 14:29:59.999000",
        "type": "sl",
        "price": 0.006800744131456165,
        "pct": -1.008
      }
    ],
    "last_ts": "2026-06-22 14:29:59.999000",
    "closed_at": "2026-06-22T14:32:32"
  },
  {
    "id": "1782136874975",
    "symbol": "SEIUSDT",
    "label": "RSI70 · 15m",
    "strategy": "classic",
    "timeframe": "15m",
    "side": "buy",
    "entry": 0.05645,
    "stop": 0.056053572516512266,
    "stop_orig": 0.056053572516512266,
    "targets": [
      0.056926,
      0.0575315,
      0.0592815
    ],
    "risk": 0.00039642748348773377,
    "opened_at": "2026-06-22T14:02:27",
    "status": "closed",
    "hits": [],
    "breakeven": false,
    "remaining": 0.0,
    "realized_pct": -0.7022630354078544,
    "result_pct": -0.702,
    "exit_price": 0.056053572516512266,
    "events": [
      {
        "ts": "2026-06-22 14:14:59.999000",
        "type": "sl",
        "price": 0.056053572516512266,
        "pct": -0.702
      }
    ],
    "last_ts": "2026-06-22 14:14:59.999000",
    "closed_at": "2026-06-22T14:17:34"
  },
  {
    "id": "1782136875199",
    "symbol": "SSVUSDT",
    "label": "RSI70 · 15m",
    "strategy": "classic",
    "timeframe": "15m",
    "side": "buy",
    "entry": 2.416,
    "stop": 2.3963683035497443,
    "stop_orig": 2.3963683035497443,
    "targets": [
      2.4432,
      2.4778,
      2.5778
    ],
    "risk": 0.019631696450255642,
    "opened_at": "2026-06-22T14:02:27",
    "status": "closed",
    "hits": [],
    "breakeven": false,
    "remaining": 0.0,
    "realized_pct": -0.8125702173119057,
    "result_pct": -0.813,
    "exit_price": 2.3963683035497443,
    "events": [
      {
        "ts": "2026-06-22 14:29:59.999000",
        "type": "sl",
        "price": 2.3963683035497443,
        "pct": -0.813
      }
    ],
    "last_ts": "2026-06-22 14:29:59.999000",
    "closed_at": "2026-06-22T14:32:33"
  },
  {
    "id": "1782136876344",
    "symbol": "VANAUSDT",
    "label": "RSI70 · 15m",
    "strategy": "classic",
    "timeframe": "15m",
    "side": "buy",
    "entry": 1.162,
    "stop": 1.1567154643565494,
    "stop_orig": 1.1567154643565494,
    "targets": [
      1.169616,
      1.179304,
      1.207304
    ],
    "risk": 0.00528453564345055,
    "opened_at": "2026-06-22T14:02:27",
    "status": "closed",
    "hits": [],
    "breakeven": false,
    "remaining": 0.0,
    "realized_pct": -0.4547793152711317,
    "result_pct": -0.455,
    "exit_price": 1.1567154643565494,
    "events": [
      {
        "ts": "2026-06-22 14:14:59.999000",
        "type": "sl",
        "price": 1.1567154643565494,
        "pct": -0.455
      }
    ],
    "last_ts": "2026-06-22 14:14:59.999000",
    "closed_at": "2026-06-22T14:17:35"
  },
  {
    "id": "1782136877364",
    "symbol": "XRPUSDT",
    "label": "RSI70 · 15m",
    "strategy": "classic",
    "timeframe": "15m",
    "side": "buy",
    "entry": 1.1637,
    "stop": 1.1566674205918224,
    "stop_orig": 1.1566674205918224,
    "targets": [
      1.1721048,
      1.1827962,
      1.2136962
    ],
    "risk": 0.007032579408177586,
    "opened_at": "2026-06-22T14:02:27",
    "status": "closed",
    "hits": [],
    "breakeven": false,
    "remaining": 0.0,
    "realized_pct": -0.60432924363475,
    "result_pct": -0.604,
    "exit_price": 1.1566674205918224,
    "events": [
      {
        "ts": "2026-06-22 14:14:59.999000",
        "type": "sl",
        "price": 1.1566674205918224,
        "pct": -0.604
      }
    ],
    "last_ts": "2026-06-22 14:14:59.999000",
    "closed_at": "2026-06-22T14:17:36"
  },
  {
    "id": "1782136878290",
    "symbol": "ZENUSDT",
    "label": "RSI70 · 15m",
    "strategy": "classic",
    "timeframe": "15m",
    "side": "buy",
    "entry": 4.711,
    "stop": 4.679517632976213,
    "stop_orig": 4.679517632976213,
    "targets": [
      4.742824,
      4.783306,
      4.900306
    ],
    "risk": 0.03148236702378693,
    "opened_at": "2026-06-22T14:02:27",
    "status": "closed",
    "hits": [],
    "breakeven": false,
    "remaining": 0.0,
    "realized_pct": -0.6682735517679246,
    "result_pct": -0.668,
    "exit_price": 4.679517632976213,
    "events": [
      {
        "ts": "2026-06-22 14:14:59.999000",
        "type": "sl",
        "price": 4.679517632976213,
        "pct": -0.668
      }
    ],
    "last_ts": "2026-06-22 14:14:59.999000",
    "closed_at": "2026-06-22T14:17:37"
  },
  {
    "id": "1782136898575",
    "symbol": "ZROUSDT",
    "label": "RSI70 · 1h",
    "strategy": "classic",
    "timeframe": "1h",
    "side": "buy",
    "entry": 0.991,
    "stop": 0.9681815634586154,
    "stop_orig": 0.9681815634586154,
    "targets": [
      1.014936,
      1.045384,
      1.133384
    ],
    "risk": 0.0228184365413846,
    "opened_at": "2026-06-22T14:02:27",
    "status": "open",
    "hits": [],
    "breakeven": false,
    "remaining": 1.0,
    "realized_pct": 0.0,
    "result_pct": null,
    "exit_price": null,
    "events": [],
    "last_ts": "2026-06-22 15:59:59.999000",
    "closed_at": null
  },
  {
    "id": "1782137760170",
    "symbol": "CELRUSDT",
    "label": "RSI70 · 15m",
    "strategy": "classic",
    "timeframe": "15m",
    "side": "buy",
    "entry": 0.002113,
    "stop": 0.002097807919714237,
    "stop_orig": 0.002097807919714237,
    "targets": [
      0.00212878,
      0.00214884,
      0.00220684
    ],
    "risk": 1.5192080285762657e-05,
    "opened_at": "2026-06-22T14:17:19",
    "status": "closed",
    "hits": [],
    "breakeven": false,
    "remaining": 0.0,
    "realized_pct": -0.7189815563541248,
    "result_pct": -0.719,
    "exit_price": 0.002097807919714237,
    "events": [
      {
        "ts": "2026-06-22 14:44:59.999000",
        "type": "sl",
        "price": 0.002097807919714237,
        "pct": -0.719
      }
    ],
    "last_ts": "2026-06-22 14:44:59.999000",
    "closed_at": "2026-06-22T14:47:15"
  },
  {
    "id": "1782137761272",
    "symbol": "HIVEUSDT",
    "label": "RSI70 · 15m",
    "strategy": "classic",
    "timeframe": "15m",
    "side": "buy",
    "entry": 0.0506,
    "stop": 0.050269925352316246,
    "stop_orig": 0.050269925352316246,
    "targets": [
      0.0510624,
      0.0516506,
      0.0533506
    ],
    "risk": 0.0003300746476837535,
    "opened_at": "2026-06-22T14:17:19",
    "status": "closed",
    "hits": [],
    "breakeven": false,
    "remaining": 0.0,
    "realized_pct": -0.6523214381101848,
    "result_pct": -0.652,
    "exit_price": 0.050269925352316246,
    "events": [
      {
        "ts": "2026-06-22 14:29:59.999000",
        "type": "sl",
        "price": 0.050269925352316246,
        "pct": -0.652
      }
    ],
    "last_ts": "2026-06-22 14:29:59.999000",
    "closed_at": "2026-06-22T14:32:35"
  },
  {
    "id": "1782137762415",
    "symbol": "PARTIUSDT",
    "label": "RSI70 · 15m",
    "strategy": "classic",
    "timeframe": "15m",
    "side": "buy",
    "entry": 0.0618,
    "stop": 0.06092154338811551,
    "stop_orig": 0.06092154338811551,
    "targets": [
      0.0630784,
      0.0647046,
      0.0694046
    ],
    "risk": 0.0008784566118844941,
    "opened_at": "2026-06-22T14:17:19",
    "status": "closed",
    "hits": [],
    "breakeven": false,
    "remaining": 0.0,
    "realized_pct": -1.4214508282920617,
    "result_pct": -1.421,
    "exit_price": 0.06092154338811551,
    "events": [
      {
        "ts": "2026-06-22 14:44:59.999000",
        "type": "sl",
        "price": 0.06092154338811551,
        "pct": -1.421
      }
    ],
    "last_ts": "2026-06-22 14:44:59.999000",
    "closed_at": "2026-06-22T14:47:16"
  },
  {
    "id": "1782137763568",
    "symbol": "SIGNUSDT",
    "label": "RSI70 · 15m",
    "strategy": "classic",
    "timeframe": "15m",
    "side": "buy",
    "entry": 0.00945,
    "stop": 0.00945,
    "stop_orig": 0.009381527014492722,
    "targets": [
      0.00956424,
      0.00970956,
      0.01012956
    ],
    "risk": 6.847298550727819e-05,
    "opened_at": "2026-06-22T14:17:19",
    "status": "open",
    "hits": [
      1
    ],
    "breakeven": true,
    "remaining": 1.0,
    "realized_pct": 0.0,
    "result_pct": null,
    "exit_price": null,
    "events": [
      {
        "ts": "2026-06-22 15:14:59.999000",
        "type": "tp1_be",
        "price": 0.00956424,
        "pct": 1.209
      }
    ],
    "last_ts": "2026-06-22 16:29:59.999000",
    "closed_at": null
  },
  {
    "id": "1782137764905",
    "symbol": "TRXUSDT",
    "label": "RSI70 · 15m",
    "strategy": "classic",
    "timeframe": "15m",
    "side": "buy",
    "entry": 0.3319,
    "stop": 0.33133943959746553,
    "stop_orig": 0.33133943959746553,
    "targets": [
      0.3322808,
      0.3327652,
      0.3341652
    ],
    "risk": 0.000560560402534438,
    "opened_at": "2026-06-22T14:17:19",
    "status": "closed",
    "hits": [],
    "breakeven": false,
    "remaining": 0.0,
    "realized_pct": -0.16889436653643808,
    "result_pct": -0.169,
    "exit_price": 0.33133943959746553,
    "events": [
      {
        "ts": "2026-06-22 15:59:59.999000",
        "type": "sl",
        "price": 0.33133943959746553,
        "pct": -0.169
      }
    ],
    "last_ts": "2026-06-22 15:59:59.999000",
    "closed_at": "2026-06-22T16:02:30"
  },
  {
    "id": "1782137765346",
    "symbol": "VETUSDT",
    "label": "RSI70 · 15m",
    "strategy": "classic",
    "timeframe": "15m",
    "side": "buy",
    "entry": 0.005052,
    "stop": 0.00501568856750519,
    "stop_orig": 0.00501568856750519,
    "targets": [
      0.00509606,
      0.00515212,
      0.00531412
    ],
    "risk": 3.631143249480974e-05,
    "opened_at": "2026-06-22T14:17:19",
    "status": "closed",
    "hits": [],
    "breakeven": false,
    "remaining": 0.0,
    "realized_pct": -0.7187536123279837,
    "result_pct": -0.719,
    "exit_price": 0.00501568856750519,
    "events": [
      {
        "ts": "2026-06-22 14:29:59.999000",
        "type": "sl",
        "price": 0.00501568856750519,
        "pct": -0.719
      }
    ],
    "last_ts": "2026-06-22 14:29:59.999000",
    "closed_at": "2026-06-22T14:32:37"
  },
  {
    "id": "1782140468544",
    "symbol": "CUSDT",
    "label": "RSI70 · 15m",
    "strategy": "classic",
    "timeframe": "15m",
    "side": "buy",
    "entry": 0.0968,
    "stop": 0.09454131,
    "stop_orig": 0.09454131,
    "targets": [
      0.0978336,
      0.0991484,
      0.1029484
    ],
    "risk": 0.0022586899999999938,
    "opened_at": "2026-06-22T15:02:08",
    "status": "closed",
    "hits": [],
    "breakeven": false,
    "remaining": 0.0,
    "realized_pct": -2.3333574380165225,
    "result_pct": -2.333,
    "exit_price": 0.09454131,
    "events": [
      {
        "ts": "2026-06-22 15:59:59.999000",
        "type": "sl",
        "price": 0.09454131,
        "pct": -2.333
      }
    ],
    "last_ts": "2026-06-22 15:59:59.999000",
    "closed_at": "2026-06-22T16:02:31"
  },
  {
    "id": "1782140488941",
    "symbol": "TIAUSDT",
    "label": "RSI70 · 1h",
    "strategy": "classic",
    "timeframe": "1h",
    "side": "buy",
    "entry": 0.4086,
    "stop": 0.38131902,
    "stop_orig": 0.38131902,
    "targets": [
      0.4215472,
      0.4380168,
      0.4856168
    ],
    "risk": 0.02728098000000001,
    "opened_at": "2026-06-22T15:02:08",
    "status": "open",
    "hits": [],
    "breakeven": false,
    "remaining": 1.0,
    "realized_pct": 0.0,
    "result_pct": null,
    "exit_price": null,
    "events": [],
    "last_ts": "2026-06-22 15:59:59.999000",
    "closed_at": null
  },
  {
    "id": "1782142269993",
    "symbol": "CUSDT",
    "label": "RSI70 · 15m",
    "strategy": "classic",
    "timeframe": "15m",
    "side": "buy",
    "entry": 0.0973,
    "stop": 0.09477874,
    "stop_orig": 0.09477874,
    "targets": [
      0.0984696,
      0.0999574,
      0.1042574
    ],
    "risk": 0.0025212599999999974,
    "opened_at": "2026-06-22T15:32:19",
    "status": "closed",
    "hits": [],
    "breakeven": false,
    "remaining": 0.0,
    "realized_pct": -2.5912230215827314,
    "result_pct": -2.591,
    "exit_price": 0.09477874,
    "events": [
      {
        "ts": "2026-06-22 15:59:59.999000",
        "type": "sl",
        "price": 0.09477874,
        "pct": -2.591
      }
    ],
    "last_ts": "2026-06-22 15:59:59.999000",
    "closed_at": "2026-06-22T16:02:33"
  },
  {
    "id": "1782142270761",
    "symbol": "ENSOUSDT",
    "label": "RSI70 · 15m",
    "strategy": "classic",
    "timeframe": "15m",
    "side": "buy",
    "entry": 0.641,
    "stop": 0.641,
    "stop_orig": 0.62347474,
    "targets": [
      0.648344,
      0.657686,
      0.684686
    ],
    "risk": 0.017525259999999987,
    "opened_at": "2026-06-22T15:32:19",
    "status": "open",
    "hits": [
      1
    ],
    "breakeven": true,
    "remaining": 1.0,
    "realized_pct": 0.0,
    "result_pct": null,
    "exit_price": null,
    "events": [
      {
        "ts": "2026-06-22 15:44:59.999000",
        "type": "tp1_be",
        "price": 0.648344,
        "pct": 1.146
      }
    ],
    "last_ts": "2026-06-22 16:29:59.999000",
    "closed_at": null
  },
  {
    "id": "1782143155803",
    "symbol": "ARPAUSDT",
    "label": "RSI70 · 15m",
    "strategy": "classic",
    "timeframe": "15m",
    "side": "buy",
    "entry": 0.00933,
    "stop": 0.00888274,
    "stop_orig": 0.00888274,
    "targets": [
      0.009534,
      0.0097935,
      0.0105435
    ],
    "risk": 0.00044725999999999967,
    "opened_at": "2026-06-22T15:47:04",
    "status": "open",
    "hits": [],
    "breakeven": false,
    "remaining": 1.0,
    "realized_pct": 0.0,
    "result_pct": null,
    "exit_price": null,
    "events": [],
    "last_ts": "2026-06-22 16:29:59.999000",
    "closed_at": null
  },
  {
    "id": "1782143156212",
    "symbol": "POLUSDT",
    "label": "RSI70 · 15m",
    "strategy": "classic",
    "timeframe": "15m",
    "side": "buy",
    "entry": 0.08217,
    "stop": 0.08060167,
    "stop_orig": 0.08060167,
    "targets": [
      0.0829044,
      0.0838386,
      0.0865386
    ],
    "risk": 0.0015683300000000067,
    "opened_at": "2026-06-22T15:47:04",
    "status": "open",
    "hits": [],
    "breakeven": false,
    "remaining": 1.0,
    "realized_pct": 0.0,
    "result_pct": null,
    "exit_price": null,
    "events": [],
    "last_ts": "2026-06-22 16:29:59.999000",
    "closed_at": null
  },
  {
    "id": "1782144097122",
    "symbol": "ARPAUSDT",
    "label": "RSI70 · 1h",
    "strategy": "classic",
    "timeframe": "1h",
    "side": "buy",
    "entry": 0.00926,
    "stop": 0.00873737,
    "stop_orig": 0.00873737,
    "targets": [
      0.00949936,
      0.00980384,
      0.01068384
    ],
    "risk": 0.0005226299999999996,
    "opened_at": "2026-06-22T16:02:22",
    "status": "open",
    "hits": [],
    "breakeven": false,
    "remaining": 1.0,
    "realized_pct": 0.0,
    "result_pct": null,
    "exit_price": null,
    "events": [],
    "last_ts": "2026-06-22 15:59:59.999000",
    "closed_at": null
  },
  {
    "id": "1782144098475",
    "symbol": "AWEUSDT",
    "label": "RSI70 · 1h",
    "strategy": "classic",
    "timeframe": "1h",
    "side": "buy",
    "entry": 0.05908,
    "stop": 0.05693525,
    "stop_orig": 0.05693525,
    "targets": [
      0.06008096,
      0.06135424,
      0.06503424
    ],
    "risk": 0.002144750000000001,
    "opened_at": "2026-06-22T16:02:22",
    "status": "open",
    "hits": [],
    "breakeven": false,
    "remaining": 1.0,
    "realized_pct": 0.0,
    "result_pct": null,
    "exit_price": null,
    "events": [],
    "last_ts": "2026-06-22 15:59:59.999000",
    "closed_at": null
  },
  {
    "id": "1782144099390",
    "symbol": "BREVUSDT",
    "label": "RSI70 · 1h",
    "strategy": "classic",
    "timeframe": "1h",
    "side": "buy",
    "entry": 0.0879,
    "stop": 0.08231356,
    "stop_orig": 0.08231356,
    "targets": [
      0.090484,
      0.093771,
      0.103271
    ],
    "risk": 0.005586440000000012,
    "opened_at": "2026-06-22T16:02:22",
    "status": "open",
    "hits": [],
    "breakeven": false,
    "remaining": 1.0,
    "realized_pct": 0.0,
    "result_pct": null,
    "exit_price": null,
    "events": [],
    "last_ts": "2026-06-22 15:59:59.999000",
    "closed_at": null
  },
  {
    "id": "1782144966631",
    "symbol": "BREVUSDT",
    "label": "RSI70 · 15m",
    "strategy": "classic",
    "timeframe": "15m",
    "side": "buy",
    "entry": 0.0911,
    "stop": 0.08499145,
    "stop_orig": 0.08499145,
    "targets": [
      0.0939832,
      0.0976508,
      0.1082508
    ],
    "risk": 0.006108550000000004,
    "opened_at": "2026-06-22T16:17:35",
    "status": "open",
    "hits": [],
    "breakeven": false,
    "remaining": 1.0,
    "realized_pct": 0.0,
    "result_pct": null,
    "exit_price": null,
    "events": [],
    "last_ts": "2026-06-22 16:29:59.999000",
    "closed_at": null
  },
  {
    "id": "1782145871582",
    "symbol": "ENJUSDT",
    "label": "RSI70 · 15m",
    "strategy": "classic",
    "timeframe": "15m",
    "side": "buy",
    "entry": 0.03435,
    "stop": 0.03350229,
    "stop_orig": 0.03350229,
    "targets": [
      0.03474712,
      0.03525228,
      0.03671228
    ],
    "risk": 0.0008477100000000015,
    "opened_at": "2026-06-22T16:32:43",
    "status": "open",
    "hits": [],
    "breakeven": false,
    "remaining": 1.0,
    "realized_pct": 0.0,
    "result_pct": null,
    "exit_price": null,
    "events": [],
    "last_ts": "2026-06-22 16:29:59.999000",
    "closed_at": null
  },
  {
    "id": "1782145872324",
    "symbol": "SIGNUSDT",
    "label": "RSI70 · 15m",
    "strategy": "classic",
    "timeframe": "15m",
    "side": "buy",
    "entry": 0.0097,
    "stop": 0.00935762,
    "stop_orig": 0.00935762,
    "targets": [
      0.0098632,
      0.0100708,
      0.0106708
    ],
    "risk": 0.00034237999999999977,
    "opened_at": "2026-06-22T16:32:43",
    "status": "open",
    "hits": [],
    "breakeven": false,
    "remaining": 1.0,
    "realized_pct": 0.0,
    "result_pct": null,
    "exit_price": null,
    "events": [],
    "last_ts": "2026-06-22 16:29:59.999000",
    "closed_at": null
  }
]